config.toml
python_accounting/config.py
python_accounting/database/__init__.py
python_accounting/database/accounting_functions.py
python_accounting/database/database_init.py
python_accounting/database/engine.py
python_accounting/database/event_listeners.py
python_accounting/database/session.py
python_accounting/database/session_overrides.py
python_accounting/exceptions/__init__.py
python_accounting/mixins/__init__.py
python_accounting/mixins/assigning.py
python_accounting/mixins/buying.py
python_accounting/mixins/clearing.py
python_accounting/mixins/isolating.py
python_accounting/mixins/selling.py
python_accounting/mixins/trading.py
python_accounting/models/__init__.py
python_accounting/models/account.py
python_accounting/models/assignment.py
python_accounting/models/balance.py
python_accounting/models/base.py
python_accounting/models/category.py
python_accounting/models/currency.py
python_accounting/models/entity.py
python_accounting/models/ledger.py
python_accounting/models/line_item.py
python_accounting/models/recyclable.py
python_accounting/models/recycled.py
python_accounting/models/reporting_period.py
python_accounting/models/tax.py
python_accounting/models/transaction.py
python_accounting/models/user.py
python_accounting/reports/__init__.py
python_accounting/reports/aging_schedule.py
python_accounting/reports/balance_sheet.py
python_accounting/reports/cashflow_statement.py
python_accounting/reports/financial_statement.py
python_accounting/reports/income_statement.py
python_accounting/reports/trial_balance.py
python_accounting/transactions/__init__.py
python_accounting/transactions/cash_purchase.py
python_accounting/transactions/cash_sale.py
python_accounting/transactions/client_invoice.py
python_accounting/transactions/client_receipt.py
python_accounting/transactions/contra_entry.py
python_accounting/transactions/credit_note.py
python_accounting/transactions/debit_note.py
python_accounting/transactions/journal_entry.py
python_accounting-1.0.1.dist-info/LICENSE
python_accounting-1.0.1.dist-info/METADATA
python_accounting-1.0.1.dist-info/WHEEL
python_accounting-1.0.1.dist-info/RECORD
