Metadata-Version: 2.1
Name: python-accounting
Version: 1.0.1
Summary: The world's most comprehensive python Double Entry Accounting Library
Author: Edward Mungai
Author-email: emungai@microbooks.io
Requires-Python: >=3.9.0,<3.13.0
Classifier: Programming Language :: Python :: 3
Classifier: Programming Language :: Python :: 3.9
Classifier: Programming Language :: Python :: 3.10
Classifier: Programming Language :: Python :: 3.11
Classifier: Programming Language :: Python :: 3.12
Requires-Dist: mysqlclient (>=2.2.4,<3.0.0)
Requires-Dist: psycopg2 (>=2.9.9,<3.0.0)
Requires-Dist: python-dateutil (>=2.8.2,<3.0.0)
Requires-Dist: sqlalchemy (>=2.0.23,<3.0.0)
Requires-Dist: strenum (>=0.4.15,<0.5.0)
Requires-Dist: toml (>=0.10.2,<0.11.0)
